pgkit/__init__.py
pgkit/application/__init__.py
pgkit/application/db.py
pgkit/application/models/__init__.py
pgkit/application/models/master.py
pgkit/application/models/postgres.py
pgkit/application/models/replica.py
pgkit/application/pg.py
pgkit/application/settings.py
pgkit/application/templates/10-recovery.conf
pgkit/application/templates/11-recovery.conf
pgkit/application/templates/12-recovery.conf
pgkit/application/templates/13-recovery.conf
pgkit/application/templates/14-recovery.conf
pgkit/application/templates/15-recovery.conf
pgkit/application/templates/9.5-recovery.conf
pgkit/application/templates/__init__.py
pgkit/application/templates/wal-receive-service.service
pgkit/application/utils.py
pgkit/cli/__init__.py
pgkit/cli/cli.py
pgkit/cli/commands/__init__.py
pgkit/cli/commands/config.py
pgkit/cli/commands/pitr.py
pgkit/cli/commands/shellx.py
pgkit-2.3.0.dist-info/LICENSE
pgkit-2.3.0.dist-info/METADATA
pgkit-2.3.0.dist-info/WHEEL
pgkit-2.3.0.dist-info/entry_points.txt
pgkit-2.3.0.dist-info/RECORD
