Metadata-Version: 2.1
Name: pgkit
Version: 2.3.0
Summary: 
License: MIT
Author: Sadegh Hayeri
Author-email: hayerisadegh@gmail.com
Requires-Python: >=3.8,<4.0
Classifier: License :: OSI Approved :: MIT License
Classifier: Programming Language :: Python :: 3
Classifier: Programming Language :: Python :: 3.8
Classifier: Programming Language :: Python :: 3.9
Classifier: Programming Language :: Python :: 3.10
Classifier: Programming Language :: Python :: 3.11
Requires-Dist: Jinja2 (==3.0.3)
Requires-Dist: PyYAML (>=6.0,<7.0)
Requires-Dist: click (>=7.1.2,<8.0.0)
Requires-Dist: python-dateutil (>=2.8.1,<3.0.0)
Requires-Dist: pytz (>=2021.1,<2022.0)
Requires-Dist: tinydb (>=4.3.0,<5.0.0)
